gwbase/__init__.py
gwbase/actor_base.py
gwbase/codec.py
gwbase/config/__init__.py
gwbase/config/algo_settings.py
gwbase/config/g_node_settings.py
gwbase/config/rabbit_settings.py
gwbase/config/utils.py
gwbase/data_classes/.DS_Store
gwbase/data_classes/__init__.py
gwbase/data_classes/base_g_node.py
gwbase/data_classes/g_node.py
gwbase/data_classes/g_node_instance.py
gwbase/data_classes/g_node_strategy.py
gwbase/data_classes/gps_point.py
gwbase/data_classes/supervisor_container.py
gwbase/enums/.DS_Store
gwbase/enums/__init__.py
gwbase/enums/core_g_node_role.py
gwbase/enums/g_node_role.py
gwbase/enums/g_node_status.py
gwbase/enums/gni_status.py
gwbase/enums/message_category.py
gwbase/enums/message_category_symbol.py
gwbase/enums/strategy_name.py
gwbase/enums/supervisor_container_status.py
gwbase/enums/universe_type.py
gwbase/named_types/__init__.py
gwbase/named_types/asl_types.py
gwbase/named_types/base_g_node_gt.py
gwbase/named_types/g_node_gt.py
gwbase/named_types/g_node_instance_gt.py
gwbase/named_types/heartbeat_a.py
gwbase/named_types/ready.py
gwbase/named_types/sim_timestep.py
gwbase/named_types/super_starter.py
gwbase/named_types/supervisor_container_gt.py
gwbase/property_format.py
gwbase/py.typed
gwbase_test/.DS_Store
gwbase_test/__init__.py
gwbase_test/stub_actors.py
gridworks_base-0.3.5.dist-info/LICENSE
gridworks_base-0.3.5.dist-info/METADATA
gridworks_base-0.3.5.dist-info/WHEEL
gridworks_base-0.3.5.dist-info/RECORD
