Metadata-Version: 2.1
Name: gridworks-base
Version: 0.3.5
Summary: Gridworks Base
Home-page: https://github.com/thegridelectric/gridworks-base
License: MIT
Author: GridWorks
Author-email: gridworks@gridworks-consulting.com
Requires-Python: >=3.11,<4.0
Classifier: Development Status :: 2 - Pre-Alpha
Classifier: License :: OSI Approved :: MIT License
Classifier: Programming Language :: Python :: 3
Classifier: Programming Language :: Python :: 3.11
Classifier: Programming Language :: Python :: 3.12
Requires-Dist: gridworks (==1.4.2)
Requires-Dist: pika (>=1.3.2,<2.0.0)
Requires-Dist: py-algorand-sdk (>=2.6.1)
Requires-Dist: pydantic (>=2.8.2,<3.0.0)
Requires-Dist: pydantic-settings (>=2.3.4,<3.0.0)
Requires-Dist: python-dotenv (>=1.0.0)
Project-URL: Changelog, https://github.com/thegridelectric/gridworks-base/releases
Project-URL: Documentation, https://gridworks-base.readthedocs.io
Project-URL: Repository, https://github.com/thegridelectric/gridworks-base
